multiple_loss/__init__.py
multiple_loss/contrastive_loss.py
multiple_loss/multilabelloss.py
multiple_loss-0.0.7.dist-info/LICENSE
multiple_loss-0.0.7.dist-info/METADATA
multiple_loss-0.0.7.dist-info/WHEEL
multiple_loss-0.0.7.dist-info/top_level.txt
multiple_loss-0.0.7.dist-info/RECORD
