Metadata-Version: 2.1
Name: multiple-loss
Version: 0.0.7
Summary: it's implimentation of multiple loss
Home-page: https://github.com/omkarsingh1008/multi_label_loss_pypi
Author: omkarsingh1008
Author-email: omkarsinghrajpurohit363@gmail.com
License: UNKNOWN
Project-URL: Bug Tracker, https://github.com/omkarsingh1008/multi_label_loss_pypi/issues
Platform: UNKNOWN
Classifier: Programming Language :: Python :: 3
Classifier: License :: OSI Approved :: MIT License
Classifier: Operating System :: OS Independent
Requires-Python: >=3.7
License-File: LICENSE
